radin/__init__.py
RaDinDBase-0.0.1.dist-info/LICENSE
RaDinDBase-0.0.1.dist-info/METADATA
RaDinDBase-0.0.1.dist-info/WHEEL
RaDinDBase-0.0.1.dist-info/top_level.txt
RaDinDBase-0.0.1.dist-info/RECORD
