Metadata-Version: 2.1
Name: RaDinDBase
Version: 0.0.1
Summary: It's a School's Database Modifier, That is written by Abuzar Alvi.
Author: Abuzar
Author-email: radinofficial15@gmail.com
Keywords: school,database,school database,arithmetic,mathematics,python,RaDin,RaDin database,database modifier
Classifier: Development Status :: 1 - Planning
Classifier: Intended Audience :: Developers
Classifier: Programming Language :: Python :: 3
Classifier: Operating System :: Unix
Classifier: Operating System :: MacOS :: MacOS X
Classifier: Operating System :: Microsoft :: Windows
License-File: LICENSE
Requires-Dist: sqlite3 >=3.43.0
Requires-Dist: datetime >=5.2
Requires-Dist: calendar >=3.11.5
